[
    {
        "id": 1,
        "firstName": "Wendell",
        "lastName": "Stackhouse"
    },
    {
        "id": 2,
        "firstName": "Amelia",
        "lastName": "Wangerin, Jr."
    },
    {
        "id": 3,
        "firstName": "Anastasia",
        "lastName": "Inez"
    },
    {
        "id": 4,
        "firstName": "Arthur",
        "lastName": "McCrumb"
    },
    {
        "id": 5,
        "firstName": "Arturo",
        "lastName": "Hijuelos"
    },
    {
        "id": 6,
        "firstName": "Bernard",
        "lastName": "Hopf"
    },
    {
        "id": 7,
        "firstName": "Bianca",
        "lastName": "Thompson"
    },
    {
        "id": 8,
        "firstName": "Bravig",
        "lastName": "Lewisohn"
    },
    {
        "id": 9,
        "firstName": "Burton",
        "lastName": "Malamud"
    },
    {
        "id": 10,
        "firstName": "Carolyn",
        "lastName": "Segal"
    },
    {
        "id": 11,
        "firstName": "Charles",
        "lastName": "Fenimore"
    },
    {
        "id": 12,
        "firstName": "Clifford",
        "lastName": "Wolitzer"
    },
    {
        "id": 13,
        "firstName": "Darryl",
        "lastName": "Fleischman"
    },
    {
        "id": 14,
        "firstName": "David",
        "lastName": "Beam"
    },
    {
        "id": 15,
        "firstName": "Elizabeth",
        "lastName": "Herbach"
    },
    {
        "id": 16,
        "firstName": "Elmer",
        "lastName": "Komroff"
    },
    {
        "id": 17,
        "firstName": "Gloria",
        "lastName": "Green"
    },
    {
        "id": 18,
        "firstName": "Grace",
        "lastName": "Harrison"
    },
    {
        "id": 19,
        "firstName": "Hamlin",
        "lastName": "Myrer"
    },
    {
        "id": 20,
        "firstName": "Hillary",
        "lastName": "Barnhardt"
    },
    {
        "id": 21,
        "firstName": "Jill",
        "lastName": "Hergesheimer"
    },
    {
        "id": 22,
        "firstName": "John W.",
        "lastName": "Spanogle"
    },
    {
        "id": 23,
        "firstName": "Jonathan",
        "lastName": "Kotzwinkle"
    },
    {
        "id": 24,
        "firstName": "Kathy",
        "lastName": "Yglesias"
    },
    {
        "id": 25,
        "firstName": "Kenneth",
        "lastName": "Douglas"
    },
    {
        "id": 26,
        "firstName": "Kris",
        "lastName": "Elegant"
    },
    {
        "id": 27,
        "firstName": "Langston",
        "lastName": "Lippman"
    },
    {
        "id": 28,
        "firstName": "Leonard",
        "lastName": "Nabokov"
    },
    {
        "id": 29,
        "firstName": "Lori",
        "lastName": "Kaan"
    },
    {
        "id": 30,
        "firstName": "Lynne",
        "lastName": "Danticat"
    },
    {
        "id": 31,
        "firstName": "Malin",
        "lastName": "Wolff"
    },
    {
        "id": 32,
        "firstName": "Oliver",
        "lastName": "Lowry"
    },
    {
        "id": 33,
        "firstName": "Patricia",
        "lastName": "Hazzard"
    },
    {
        "id": 34,
        "firstName": "Philip",
        "lastName": "Antrim"
    },
    {
        "id": 35,
        "firstName": "Phoebe",
        "lastName": "Brown"
    },
    {
        "id": 36,
        "firstName": "R.M.",
        "lastName": "Larner"
    },
    {
        "id": 37,
        "firstName": "Robert",
        "lastName": "Plimpton"
    },
    {
        "id": 38,
        "firstName": "Robert",
        "lastName": "Milofsky"
    },
    {
        "id": 39,
        "firstName": "Ursula",
        "lastName": "Karénine"
    },
    {
        "id": 40,
        "firstName": "Ward",
        "lastName": "Haigh"
    },
    {
        "id": 41,
        "firstName": "Abraham",
        "lastName": "Barton"
    }
]